frozen_ground_fem/__init__.py
frozen_ground_fem/consolidation.py
frozen_ground_fem/coupled.py
frozen_ground_fem/geometry.py
frozen_ground_fem/materials.py
frozen_ground_fem/thermal.py
frozen_ground_fem-1.0.2.dist-info/licenses/LICENSE
frozen_ground_fem-1.0.2.dist-info/METADATA
frozen_ground_fem-1.0.2.dist-info/WHEEL
frozen_ground_fem-1.0.2.dist-info/top_level.txt
frozen_ground_fem-1.0.2.dist-info/RECORD
