Metadata-Version: 2.4
Name: frozen_ground_fem
Version: 1.0.2
Summary: Multi-physics for frozen ground analysis
Author-email: Anna Pekinasova <anna.pekinasova@ucalgary.ca>, Brandon Karchewski <brandon.karchewski@ucalgary.ca>
Project-URL: Homepage, https://github.com/annapekinasova/frozen-ground-fem
Classifier: Programming Language :: Python :: 3
Classifier: Operating System :: OS Independent
Classifier: License :: OSI Approved :: MIT License
Requires-Python: >=3.10
License-File: LICENSE
Requires-Dist: numpy>=1.22
Requires-Dist: matplotlib>=3.6
Dynamic: license-file
